callai/__init__.py
callai/api.py
callai/client.py
callai/function_calling.py
callai/session.py
callai/storage/__init__.py
callai/storage/db.py
callai/storage/json_storage.py
callai-0.2.1.dist-info/LICENSE
callai-0.2.1.dist-info/METADATA
callai-0.2.1.dist-info/WHEEL
callai-0.2.1.dist-info/top_level.txt
callai-0.2.1.dist-info/RECORD
