Metadata-Version: 2.2
Name: callai
Version: 0.2.1
Summary: 一个简单的OpenAI API兼容封装库
Home-page: https://github.com/aixiasang/callai
Author: AI中文开发者
Author-email: aixiasang@163.com
License: MIT
Classifier: Programming Language :: Python :: 3
Classifier: License :: OSI Approved :: MIT License
Classifier: Operating System :: OS Independent
Requires-Python: >=3.6
License-File: LICENSE
Requires-Dist: openai>=1.0.0
Requires-Dist: httpx
Provides-Extra: socks
Requires-Dist: httpx[socks]; extra == "socks"
Dynamic: author
Dynamic: author-email
Dynamic: classifier
Dynamic: description
Dynamic: description-content-type
Dynamic: home-page
Dynamic: requires-dist
Dynamic: requires-python
Dynamic: summary
